CHANGES.rst
CONTRIBUTORS.rst
MANIFEST.in
README.rst
setup.cfg
setup.py
docs/INSTALL.txt
docs/LICENSE.txt
src/plone/__init__.py
src/plone.mls.listing.egg-info/PKG-INFO
src/plone.mls.listing.egg-info/SOURCES.txt
src/plone.mls.listing.egg-info/dependency_links.txt
src/plone.mls.listing.egg-info/entry_points.txt
src/plone.mls.listing.egg-info/namespace_packages.txt
src/plone.mls.listing.egg-info/not-zip-safe
src/plone.mls.listing.egg-info/requires.txt
src/plone.mls.listing.egg-info/top_level.txt
src/plone/mls/__init__.py
src/plone/mls/listing/__init__.py
src/plone/mls/listing/api.py
src/plone/mls/listing/configure.zcml
src/plone/mls/listing/i18n.py
src/plone/mls/listing/interfaces.py
src/plone/mls/listing/migration.py
src/plone/mls/listing/profiles.zcml
src/plone/mls/listing/setuphandlers.py
src/plone/mls/listing/testing.py
src/plone/mls/listing/vocabularies.py
src/plone/mls/listing/browser/__init__.py
src/plone/mls/listing/browser/adapter.py
src/plone/mls/listing/browser/configure.zcml
src/plone/mls/listing/browser/controlpanel.py
src/plone/mls/listing/browser/interfaces.py
src/plone/mls/listing/browser/listing_collection.py
src/plone/mls/listing/browser/listing_search.py
src/plone/mls/listing/browser/localconfig.py
src/plone/mls/listing/browser/navigation.py
src/plone/mls/listing/browser/recent_listings.py
src/plone/mls/listing/browser/traversal.py
src/plone/mls/listing/browser/views.py
src/plone/mls/listing/browser/images/apartment.png
src/plone/mls/listing/browser/images/condominium.png
src/plone/mls/listing/browser/images/house.png
src/plone/mls/listing/browser/images/icon_talk.png
src/plone/mls/listing/browser/images/no-image.png
src/plone/mls/listing/browser/images/office-building.png
src/plone/mls/listing/browser/images/quotation_left.png
src/plone/mls/listing/browser/images/quotation_right.png
src/plone/mls/listing/browser/images/townhouse.png
src/plone/mls/listing/browser/javascript/galleria-1.2.2.js
src/plone/mls/listing/browser/javascript/jquery.ias.min.js
src/plone/mls/listing/browser/javascript/listing.js
src/plone/mls/listing/browser/javascript/listing_ias.js
src/plone/mls/listing/browser/javascript/classic/classic-loader.gif
src/plone/mls/listing/browser/javascript/classic/classic-map.png
src/plone/mls/listing/browser/javascript/classic/galleria.classic.css
